entropic/__init__.py
entropic/db/__init__.py
entropic/db/base.py
entropic/db/tiny_db.py
entropic/process/__init__.py
entropic/process/exceptions.py
entropic/process/pipeline.py
entropic/results_api/__init__.py
entropic/results_api/api.py
entropic/sources/__init__.py
entropic/sources/iteration.py
entropic/sources/sample.py
entropic/sources/fields/__init__.py
entropic/sources/fields/data_source.py
entropic-0.3.0.dist-info/METADATA
entropic-0.3.0.dist-info/WHEEL
entropic-0.3.0.dist-info/licenses/LICENSE
entropic-0.3.0.dist-info/RECORD
