Metadata-Version: 2.1
Name: entropic
Version: 0.3.0
Summary: Entropic, the simple data pipeline framework for scientists.
Project-URL: Homepage, https://github.com/jpvanegasc/entropic
Project-URL: Bug Tracker, https://github.com/jpvanegasc/entropic/issues
Project-URL: Documentation, https://entropic.readthedocs.io/en/latest/index.html
Author-email: Juan Pablo Vanegas <jpvanegasc@gmail.com>
License-Expression: MIT
License-File: LICENSE
Classifier: Development Status :: 4 - Beta
Classifier: Intended Audience :: Education
Classifier: Intended Audience :: Science/Research
Classifier: License :: OSI Approved :: MIT License
Classifier: Operating System :: OS Independent
Classifier: Programming Language :: Python :: 3
Classifier: Topic :: Scientific/Engineering
Classifier: Topic :: Utilities
Requires-Python: >=3.9
Requires-Dist: pandas[parquet]>=2.1
Requires-Dist: pydantic>=2.5
Requires-Dist: tinydb>=4.8
